notification/__init__.py
notification/mailgun.py
notification/settings.py
notification/tests.py
notification/zepto.py
notification/aws/__init__.py
notification/aws/ses.py
notification/aws/sns.py
python_notification_service-2023.3a1.dist-info/LICENSE.txt
python_notification_service-2023.3a1.dist-info/METADATA
python_notification_service-2023.3a1.dist-info/WHEEL
python_notification_service-2023.3a1.dist-info/top_level.txt
python_notification_service-2023.3a1.dist-info/RECORD
