Metadata-Version: 2.1
Name: python-notification-service
Version: 2023.3a1
Summary: Python wrapper for broadcasting messages and emails using web API protocol or similar approaches
Author: frier17
Author-email: Alpha 17 Solutions <solutions@a17s.co>
Maintainer: frier17
License: Apache License
Project-URL: repository, https://gitlab.com/frier17/python-notification-service.git
Keywords: messaging,SMS,notice,notification
Classifier: Development Status :: 4 - Beta
Classifier: Programming Language :: Python
Requires-Python: >=3.7
License-File: LICENSE.txt
Requires-Dist: requests
Requires-Dist: dotenv
